python_prompt_library/__init__.py
python_prompt_library/module.py
python_prompt_library/utils/__init__.py
python_prompt_library/utils/file_utils.py
python_prompt_library/utils/logger_utils.py
python_prompt_library/utils/string_utils.py
tests/__init__.py
tests/test_module.py
python_prompt_library-1.0.8.dist-info/LICENSE
python_prompt_library-1.0.8.dist-info/METADATA
python_prompt_library-1.0.8.dist-info/WHEEL
python_prompt_library-1.0.8.dist-info/top_level.txt
python_prompt_library-1.0.8.dist-info/RECORD
