Metadata-Version: 2.1
Name: python-prompt-library
Version: 1.0.8
Summary: A Python prompt library to consolidate libraries and utility scripts
Home-page: https://github.com/ryan-gutkowski_LPLA/Python_Prompt_Library
Author: Ryan Gutkowski
Author-email: ryan.gutkowski@lplfinancial.com
Classifier: Programming Language :: Python :: 3
Classifier: License :: OSI Approved :: MIT License
Classifier: Operating System :: OS Independent
Requires-Python: >=3.6
License-File: LICENSE
